MANIFEST.in
README.rst
setup.py
c/poly1305aes-20050218/FILES
c/poly1305aes-20050218/FILES.lib
c/poly1305aes-20050218/Makefile
c/poly1305aes-20050218/Makefile.lib
c/poly1305aes-20050218/aes.h.do
c/poly1305aes-20050218/aes_aix.h
c/poly1305aes-20050218/aes_aix.s
c/poly1305aes-20050218/aes_aix_constants.s
c/poly1305aes-20050218/aes_athlon.h
c/poly1305aes-20050218/aes_athlon.s
c/poly1305aes-20050218/aes_athlon_constants.s
c/poly1305aes-20050218/aes_big.c
c/poly1305aes-20050218/aes_big.h
c/poly1305aes-20050218/aes_big_constants.c
c/poly1305aes-20050218/aes_macos.h
c/poly1305aes-20050218/aes_macos.s
c/poly1305aes-20050218/aes_macos_constants.s
c/poly1305aes-20050218/aes_ppro.h
c/poly1305aes-20050218/aes_ppro.s
c/poly1305aes-20050218/aes_ppro_constants.s
c/poly1305aes-20050218/aes_sparc.h
c/poly1305aes-20050218/aes_sparc.s
c/poly1305aes-20050218/aes_sparc_constants.c
c/poly1305aes-20050218/cpucycles.a.do
c/poly1305aes-20050218/cpucycles.h.do
c/poly1305aes-20050218/cpucycles_aix.h
c/poly1305aes-20050218/cpucycles_aix.s
c/poly1305aes-20050218/cpucycles_athlon.h
c/poly1305aes-20050218/cpucycles_athlon.s
c/poly1305aes-20050218/cpucycles_macos.h
c/poly1305aes-20050218/cpucycles_macos.s
c/poly1305aes-20050218/cpucycles_ppro.h
c/poly1305aes-20050218/cpucycles_ppro.s
c/poly1305aes-20050218/cpucycles_sparc.h
c/poly1305aes-20050218/cpucycles_sparc.s
c/poly1305aes-20050218/cpucycles_zero.c
c/poly1305aes-20050218/cpucycles_zero.h
c/poly1305aes-20050218/poly1305.h.do
c/poly1305aes-20050218/poly1305_53.c
c/poly1305aes-20050218/poly1305_53.h
c/poly1305aes-20050218/poly1305_53_constants.c
c/poly1305aes-20050218/poly1305_aix.h
c/poly1305aes-20050218/poly1305_aix.s
c/poly1305aes-20050218/poly1305_aix_constants.c
c/poly1305aes-20050218/poly1305_athlon.h
c/poly1305aes-20050218/poly1305_athlon.s
c/poly1305aes-20050218/poly1305_athlon_constants.s
c/poly1305aes-20050218/poly1305_macos.h
c/poly1305aes-20050218/poly1305_macos.s
c/poly1305aes-20050218/poly1305_macos_constants.s
poly1305_aes.egg-info/PKG-INFO
poly1305_aes.egg-info/SOURCES.txt
poly1305_aes.egg-info/dependency_links.txt
poly1305_aes.egg-info/requires.txt
poly1305_aes.egg-info/top_level.txt
poly1305_aes.egg-info/zip-safe
