Metadata-Version: 1.1
Name: poly1305-aes
Version: 0.13.39
Summary: Python wrapper for Poly1305aes HMAC
Home-page: https://github.com/sundarnagarajan/py_poly1305aes.git
Author: Sundar Nagarajan
Author-email: UNKNOWN
License: License :: OSI Approved :: MIT License
Download-URL: https://github.com/sundarnagarajan/py_poly1305aes.git/tree/0.13.39
Platform: UNKNOWN
Classifier: Development Status :: 4 - Beta
Classifier: Programming Language :: Python :: 2
Classifier: Programming Language :: Python :: 3
Classifier: Programming Language :: Python :: Implementation :: PyPy
Classifier: License :: OSI Approved :: MIT License
Requires: cffi_utils
